tbtools/__init__.py
tbtools/read.py
tbtools/write.py
tbtools/ptrac/__init__.py
tbtools/ptrac/read.py
tbtools-0.6.dist-info/DESCRIPTION.rst
tbtools-0.6.dist-info/METADATA
tbtools-0.6.dist-info/RECORD
tbtools-0.6.dist-info/WHEEL
tbtools-0.6.dist-info/metadata.json
tbtools-0.6.dist-info/top_level.txt
