Metadata-Version: 2.0
Name: tbtools
Version: 0.6
Summary: Tools for reading/writing files associated with the TxBLEND model
Home-page: https://github.com/twdb/tbtools
Author: Taylor Sansom
Author-email: taylor.sansom@twdb.texas.gov
License: UNKNOWN
Download-URL: https://github.com/twdb/tbtools/archive/0.2.tar.gz
Keywords: TxBLEND
Platform: UNKNOWN
